MANIFEST.in
README.rst
setup.cfg
setup.py
versioneer.py
pyfigurator/__init__.py
pyfigurator/_version.py
pyfigurator/cli_options.py
pyfigurator/config.py
pyfigurator/error.py
pyfigurator.egg-info/PKG-INFO
pyfigurator.egg-info/SOURCES.txt
pyfigurator.egg-info/dependency_links.txt
pyfigurator.egg-info/requires.txt
pyfigurator.egg-info/top_level.txt