Metadata-Version: 1.1
Name: pyfigurator
Version: 0.1.0
Summary: Make it simpler to implement basic INI configuration and CLI interfaces.
Home-page: http://github.com/boehemyth/pyfigurator/
Author: Dan Boehm
Author-email: dboehm.dev@gmail.com
License: GNU General Public License v3.0
Platform: any
Classifier: Programming Language :: Python :: 3.5
Classifier: Programming Language :: Python :: 3.4
Classifier: Programming Language :: Python :: 3.3
Classifier: Development Status :: 3 - Alpha
Classifier: Natural Language :: English
Classifier: Environment :: Other Environment
Classifier: Intended Audience :: Developers
Classifier: License :: OSI Approved :: GNU General Public License v3 (GPLv3)
Classifier: Operating System :: OS Independent
Classifier: Topic :: Software Development :: Libraries :: Python Modules
Classifier: Topic :: Software Development :: User Interfaces
